<?xml version="1.0" encoding="UTF-8"?>
<channels>
  <channel site="content.astro.com.my" lang="en" xmltv_id="AdithyaTV.in" site_id="67" logo="https://divign0fdw3sv.cloudfront.net/Images/ChannelLogo/contenthub/67_144.png">Adithya</channel>
  <channel site="content.astro.com.my" lang="en" xmltv_id="AlJazeeraEnglish.qa" site_id="374" logo="https://divign0fdw3sv.cloudfront.net/Images/ChannelLogo/contenthub/374_144.png">Al Jazeera English HD</channel>
  <channel site="content.astro.com.my" lang="en" xmltv_id="AnimalPlanetSoutheastAsia.sg" site_id="377" logo="https://divign0fdw3sv.cloudfront.net/Images/ChannelLogo/contenthub/377_144.png">Animal Planet HD</channel>
  <channel site="content.astro.com.my" lang="en" xmltv_id="AsianFoodNetwork.sg" site_id="91" logo="https://divign0fdw3sv.cloudfront.net/Images/ChannelLogo/contenthub/91_144.png">Asian Food Network HD</channel>
  <channel site="content.astro.com.my" lang="en" xmltv_id="AstroAEC.my" site_id="182" logo="https://divign0fdw3sv.cloudfront.net/Images/ChannelLogo/contenthub/182_144.png">Astro AEC HD</channel>
  <channel site="content.astro.com.my" lang="en" xmltv_id="AstroAOD311.my" site_id="172" logo="https://divign0fdw3sv.cloudfront.net/Images/ChannelLogo/contenthub/172_144.png">Astro AOD 311</channel>
  <channel site="content.astro.com.my" lang="en" xmltv_id="AstroBoxOfficeThangathirai.my" site_id="177" logo="https://divign0fdw3sv.cloudfront.net/Images/ChannelLogo/contenthub/177_144.png">ABO Movies Thangathirai HD</channel>
  <channel site="content.astro.com.my" lang="en" xmltv_id="AstroHuaHeeDai.my" site_id="162" logo="https://divign0fdw3sv.cloudfront.net/Images/ChannelLogo/contenthub/162_144.png">Astro Hua Hee Dai HD</channel>
  <channel site="content.astro.com.my" lang="en" xmltv_id="AstroQuanJiaHD.my" site_id="158" logo="https://divign0fdw3sv.cloudfront.net/Images/ChannelLogo/contenthub/158_144.png">Astro QJ</channel>
  <channel site="content.astro.com.my" lang="en" xmltv_id="AstroRania.my" site_id="401" logo="https://divign0fdw3sv.cloudfront.net/Images/ChannelLogo/contenthub/401_144.png">Astro Rania HD</channel>
  <channel site="content.astro.com.my" lang="en" xmltv_id="AstroUHD.my" site_id="308" logo="https://divign0fdw3sv.cloudfront.net/Images/ChannelLogo/contenthub/308_144.png">Astro Sports UHD</channel>
  <channel site="content.astro.com.my" lang="en" xmltv_id="AstroVaanavil.my" site_id="397" logo="https://divign0fdw3sv.cloudfront.net/Images/ChannelLogo/contenthub/397_144.png">Astro Vaanavil HD</channel>
  <channel site="content.astro.com.my" lang="en" xmltv_id="AstroVellithirai.my" site_id="399" logo="https://divign0fdw3sv.cloudfront.net/Images/ChannelLogo/contenthub/399_144.png">Astro Vellithirai HD</channel>
  <channel site="content.astro.com.my" lang="en" xmltv_id="AstroVinmeenHD.my" site_id="167" logo="https://divign0fdw3sv.cloudfront.net/Images/ChannelLogo/contenthub/167_144.png">Astro Vinmeen HD</channel>
  <channel site="content.astro.com.my" lang="en" xmltv_id="AXN.my" site_id="131" logo="https://divign0fdw3sv.cloudfront.net/Images/ChannelLogo/contenthub/131_144.png">AXN HD</channel>
  <channel site="content.astro.com.my" lang="en" xmltv_id="BBCEarthAsia.uk" site_id="452" logo="https://divign0fdw3sv.cloudfront.net/Images/ChannelLogo/contenthub/452_144.png">BBC Earth</channel>
  <channel site="content.astro.com.my" lang="en" xmltv_id="BBCLifestyleAsia.uk" site_id="451" logo="https://divign0fdw3sv.cloudfront.net/Images/ChannelLogo/contenthub/451_144.png">BBC Lifestyle HD</channel>
  <channel site="content.astro.com.my" lang="en" xmltv_id="BBCNewsAsiaPacific.uk" site_id="366" logo="https://divign0fdw3sv.cloudfront.net/Images/ChannelLogo/contenthub/366_144.png">BBC News HD</channel>
  <channel site="content.astro.com.my" lang="en" xmltv_id="beINSports2.qa" site_id="466" logo="https://divign0fdw3sv.cloudfront.net/Images/ChannelLogo/contenthub/466_144.png">beIN SPORTS 2</channel>
  <channel site="content.astro.com.my" lang="en" xmltv_id="beINSports3.qa" site_id="313" logo="https://divign0fdw3sv.cloudfront.net/Images/ChannelLogo/contenthub/313_144.png">beIN SPORTS 3</channel>
  <channel site="content.astro.com.my" lang="en" xmltv_id="beINSports.qa" site_id="236" logo="https://divign0fdw3sv.cloudfront.net/Images/ChannelLogo/contenthub/236_144.png">beIN SPORTS 1</channel>
  <channel site="content.astro.com.my" lang="en" xmltv_id="BloombergTVAsia.hk" site_id="422" logo="https://divign0fdw3sv.cloudfront.net/Images/ChannelLogo/contenthub/422_144.png">Bloomberg TV HD</channel>
  <channel site="content.astro.com.my" lang="en" xmltv_id="Boo.my" site_id="251" logo="https://divign0fdw3sv.cloudfront.net/Images/ChannelLogo/contenthub/251_144.png">BOO HD</channel>
  <channel site="content.astro.com.my" lang="en" xmltv_id="CartoonNetworkAsia.sg" site_id="371" logo="https://divign0fdw3sv.cloudfront.net/Images/ChannelLogo/contenthub/371_144.png">Cartoon Network HD</channel>
  <channel site="content.astro.com.my" lang="en" xmltv_id="CCM.hk" site_id="187" logo="https://divign0fdw3sv.cloudfront.net/Images/ChannelLogo/contenthub/187_144.png">Celestial Classic Movies</channel>
  <channel site="content.astro.com.my" lang="en" xmltv_id="CCTV4Asia.cn" site_id="385" logo="https://divign0fdw3sv.cloudfront.net/Images/ChannelLogo/contenthub/385_144.png">CCTV4 HD</channel>
  <channel site="content.astro.com.my" lang="en" xmltv_id="CelestialMoviesMalaysia.my" site_id="134" logo="https://divign0fdw3sv.cloudfront.net/Images/ChannelLogo/contenthub/134_144.png">Celestial Movies HD</channel>
  <channel site="content.astro.com.my" lang="en" xmltv_id="CGTN.cn" site_id="426" logo="https://divign0fdw3sv.cloudfront.net/Images/ChannelLogo/contenthub/426_144.png">CGTN HD</channel>
  <channel site="content.astro.com.my" lang="en" xmltv_id="CinemaxAsia.sg" site_id="337" logo="https://divign0fdw3sv.cloudfront.net/Images/ChannelLogo/contenthub/337_144.png">CINEMAX HD</channel>
  <channel site="content.astro.com.my" lang="en" xmltv_id="CNA.sg" site_id="295" logo="https://divign0fdw3sv.cloudfront.net/Images/ChannelLogo/contenthub/295_144.png">CNA HD</channel>
  <channel site="content.astro.com.my" lang="en" xmltv_id="CNBCAsia.sg" site_id="423" logo="https://divign0fdw3sv.cloudfront.net/Images/ChannelLogo/contenthub/423_144.png">CNBC Asia HD</channel>
  <channel site="content.astro.com.my" lang="en" xmltv_id="CNNInternationalAsiaPacific.hk" site_id="336" logo="https://divign0fdw3sv.cloudfront.net/Images/ChannelLogo/contenthub/336_144.png">CNN HD</channel>
  <channel site="content.astro.com.my" lang="en" xmltv_id="Colors.in" site_id="365" logo="https://divign0fdw3sv.cloudfront.net/Images/ChannelLogo/contenthub/365_144.png">Colors Hindi HD</channel>
  <channel site="content.astro.com.my" lang="en" xmltv_id="ColorsTamil.in" site_id="298" logo="https://divign0fdw3sv.cloudfront.net/Images/ChannelLogo/contenthub/298_144.png">Colors Tamil HD</channel>
  <channel site="content.astro.com.my" lang="en" xmltv_id="CrimePlusInvestigationAsia.sg" site_id="369" logo="https://divign0fdw3sv.cloudfront.net/Images/ChannelLogo/contenthub/369_144.png">Crime &amp; Investigation HD</channel>
  <channel site="content.astro.com.my" lang="en" xmltv_id="CTiAsia.tw" site_id="424" logo="https://divign0fdw3sv.cloudfront.net/Images/ChannelLogo/contenthub/424_144.png">CTI Asia HD</channel>
  <channel site="content.astro.com.my" lang="en" xmltv_id="DiscoveryAsia.sg" site_id="136" logo="https://divign0fdw3sv.cloudfront.net/Images/ChannelLogo/contenthub/136_144.png">Discovery Asia HD</channel>
  <channel site="content.astro.com.my" lang="en" xmltv_id="DiscoveryChannel.id" site_id="376" logo="https://divign0fdw3sv.cloudfront.net/Images/ChannelLogo/contenthub/376_144.png">Discovery Channel HD</channel>
  <channel site="content.astro.com.my" lang="en" xmltv_id="DMAXSoutheastAsia.sg" site_id="367" logo="https://divign0fdw3sv.cloudfront.net/Images/ChannelLogo/contenthub/367_144.png">DMAX HD</channel>
  <channel site="content.astro.com.my" lang="en" xmltv_id="DWEnglish.de" site_id="287" logo="https://divign0fdw3sv.cloudfront.net/Images/ChannelLogo/contenthub/287_144.png">DW English</channel>
  <channel site="content.astro.com.my" lang="en" xmltv_id="EntertainmentNews.hk" site_id="427" logo="https://divign0fdw3sv.cloudfront.net/Images/ChannelLogo/contenthub/427_144.png">TVB Entertainment News HD</channel>
  <channel site="content.astro.com.my" lang="en" xmltv_id="EurosportAsia.fr" site_id="339" logo="https://divign0fdw3sv.cloudfront.net/Images/ChannelLogo/contenthub/339_144.png">EUROSPORT</channel>
  <channel site="content.astro.com.my" lang="en" xmltv_id="FoodNetworkAsia.sg" site_id="153" logo="https://divign0fdw3sv.cloudfront.net/Images/ChannelLogo/contenthub/153_144.png">Food Network HD</channel>
  <channel site="content.astro.com.my" lang="en" xmltv_id="France24English.fr" site_id="289" logo="https://divign0fdw3sv.cloudfront.net/Images/ChannelLogo/contenthub/289_144.png">France24</channel>
  <channel site="content.astro.com.my" lang="en" xmltv_id="GolfChannel.my" site_id="189" logo="https://divign0fdw3sv.cloudfront.net/Images/ChannelLogo/contenthub/189_144.png">Golf Channel</channel>
  <channel site="content.astro.com.my" lang="en" xmltv_id="HBOAsia.sg" site_id="143" logo="https://divign0fdw3sv.cloudfront.net/Images/ChannelLogo/contenthub/143_144.png">HBO HD</channel>
  <channel site="content.astro.com.my" lang="en" xmltv_id="HBOFamilyAsia.sg" site_id="450" logo="https://divign0fdw3sv.cloudfront.net/Images/ChannelLogo/contenthub/450_144.png">HBO Family</channel>
  <channel site="content.astro.com.my" lang="en" xmltv_id="HBOHitsAsia.sg" site_id="449" logo="https://divign0fdw3sv.cloudfront.net/Images/ChannelLogo/contenthub/449_144.png">HBO Hits</channel>
  <channel site="content.astro.com.my" lang="en" xmltv_id="HGTVAsia.us" site_id="198" logo="https://divign0fdw3sv.cloudfront.net/Images/ChannelLogo/contenthub/198_144.png">HGTV HD</channel>
  <channel site="content.astro.com.my" lang="en" xmltv_id="HistoryAsia.us" site_id="144" logo="https://divign0fdw3sv.cloudfront.net/Images/ChannelLogo/contenthub/144_144.png">History HD</channel>
  <channel site="content.astro.com.my" lang="en" xmltv_id="HITS.sg" site_id="179" logo="https://divign0fdw3sv.cloudfront.net/Images/ChannelLogo/contenthub/179_144.png">HITS HD</channel>
  <channel site="content.astro.com.my" lang="en" xmltv_id="HITSMovies.sg" site_id="391" logo="https://divign0fdw3sv.cloudfront.net/Images/ChannelLogo/contenthub/391_144.png">HITS MOVIES HD</channel>
  <channel site="content.astro.com.my" lang="en" xmltv_id="iQIYI.cn" site_id="355" logo="https://divign0fdw3sv.cloudfront.net/Images/ChannelLogo/contenthub/355_144.png">iQIYI HD</channel>
  <channel site="content.astro.com.my" lang="en" xmltv_id="Jade.hk" site_id="203" logo="https://divign0fdw3sv.cloudfront.net/Images/ChannelLogo/contenthub/203_144.png">TVB Jade</channel>
  <channel site="content.astro.com.my" lang="en" xmltv_id="KBSWorld.kr" site_id="161" logo="https://divign0fdw3sv.cloudfront.net/Images/ChannelLogo/contenthub/161_144.png">KBS World HD</channel>
  <channel site="content.astro.com.my" lang="en" xmltv_id="KPlus.sg" site_id="266" logo="https://divign0fdw3sv.cloudfront.net/Images/ChannelLogo/contenthub/266_144.png">K-Plus HD</channel>
  <channel site="content.astro.com.my" lang="en" xmltv_id="LifetimeAsia.us" site_id="447" logo="https://divign0fdw3sv.cloudfront.net/Images/ChannelLogo/contenthub/447_144.png">Lifetime HD</channel>
  <channel site="content.astro.com.my" lang="en" xmltv_id="MoonbugKids.uk" site_id="465" logo="https://divign0fdw3sv.cloudfront.net/Images/ChannelLogo/contenthub/465_144.png">Moonbug</channel>
  <channel site="content.astro.com.my" lang="en" xmltv_id="MTVAsia.sg" site_id="420" logo="https://divign0fdw3sv.cloudfront.net/Images/ChannelLogo/contenthub/420_144.png">MTV Live</channel>
  <channel site="content.astro.com.my" lang="en" xmltv_id="NHKWorldPremium.jp" site_id="428" logo="https://divign0fdw3sv.cloudfront.net/Images/ChannelLogo/contenthub/428_144.png">NHK World Premium</channel>
  <channel site="content.astro.com.my" lang="en" xmltv_id="NickelodeonAsia.sg" site_id="370" logo="https://divign0fdw3sv.cloudfront.net/Images/ChannelLogo/contenthub/370_144.png">Nickelodeon HD</channel>
  <channel site="content.astro.com.my" lang="en" xmltv_id="NickJrAsia.sg" site_id="392" logo="https://divign0fdw3sv.cloudfront.net/Images/ChannelLogo/contenthub/392_144.png">Nick Jr.</channel>
  <channel site="content.astro.com.my" lang="en" xmltv_id="ONE.sg" site_id="133" logo="https://divign0fdw3sv.cloudfront.net/Images/ChannelLogo/contenthub/133_144.png">ONE HD</channel>
  <channel site="content.astro.com.my" lang="en" xmltv_id="PhoenixChineseChannel.hk" site_id="382" logo="https://divign0fdw3sv.cloudfront.net/Images/ChannelLogo/contenthub/382_144.png">Phoenix Chinese Channel HD</channel>
  <channel site="content.astro.com.my" lang="en" xmltv_id="PhoenixInfoNewsChannel.hk" site_id="43" logo="https://divign0fdw3sv.cloudfront.net/Images/ChannelLogo/contenthub/43_144.png">Phoenix Info News HD</channel>
  <channel site="content.astro.com.my" lang="en" xmltv_id="PremierSports1Asia.ie" site_id="393" logo="https://divign0fdw3sv.cloudfront.net/Images/ChannelLogo/contenthub/393_144.png">Premier Sports Rugby</channel>
  <channel site="content.astro.com.my" lang="en" xmltv_id="ShowcaseMovies.my" site_id="454" logo="https://divign0fdw3sv.cloudfront.net/Images/ChannelLogo/contenthub/454_144.png">SHOWCASE</channel>
  <channel site="content.astro.com.my" lang="en" xmltv_id="SkyNews.uk" site_id="155" logo="https://divign0fdw3sv.cloudfront.net/Images/ChannelLogo/contenthub/155_144.png">Sky News HD</channel>
  <channel site="content.astro.com.my" lang="en" xmltv_id="SPOTV.kr" site_id="456" logo="https://divign0fdw3sv.cloudfront.net/Images/ChannelLogo/contenthub/456_144.png">SPOTV</channel>
  <channel site="content.astro.com.my" lang="en" xmltv_id="StarVijay.in" site_id="357" logo="https://divign0fdw3sv.cloudfront.net/Images/ChannelLogo/contenthub/357_144.png">Star Vijay HD</channel>
  <channel site="content.astro.com.my" lang="en" xmltv_id="SunMusic.in" site_id="417" logo="https://divign0fdw3sv.cloudfront.net/Images/ChannelLogo/contenthub/417_144.png">Sun Music HD</channel>
  <channel site="content.astro.com.my" lang="en" xmltv_id="SunTVMalaysia.my" site_id="358" logo="https://divign0fdw3sv.cloudfront.net/Images/ChannelLogo/contenthub/358_144.png">SUN TV HD</channel>
  <channel site="content.astro.com.my" lang="en" xmltv_id="TLCSoutheastAsia.sg" site_id="338" logo="https://divign0fdw3sv.cloudfront.net/Images/ChannelLogo/contenthub/338_144.png">TLC HD</channel>
  <channel site="content.astro.com.my" lang="en" xmltv_id="TVBClassic.hk" site_id="425" logo="https://divign0fdw3sv.cloudfront.net/Images/ChannelLogo/contenthub/425_144.png">TVB Classic HD</channel>
  <channel site="content.astro.com.my" lang="en" xmltv_id="TVBSAsia.tw" site_id="384" logo="https://divign0fdw3sv.cloudfront.net/Images/ChannelLogo/contenthub/384_144.png">TVBS Asia HD</channel>
  <channel site="content.astro.com.my" lang="en" xmltv_id="TVBXingHe.hk" site_id="383" logo="https://divign0fdw3sv.cloudfront.net/Images/ChannelLogo/contenthub/383_144.png">TVB Xing He HD</channel>
  <channel site="content.astro.com.my" lang="en" xmltv_id="tvNAsia.hk" site_id="190" logo="https://divign0fdw3sv.cloudfront.net/Images/ChannelLogo/contenthub/190_144.png">tvN HD</channel>
  <channel site="content.astro.com.my" lang="en" xmltv_id="tvNMoviesAsia.hk" site_id="274" logo="https://divign0fdw3sv.cloudfront.net/Images/ChannelLogo/contenthub/274_144.png">tvN Movies HD</channel>
  <channel site="content.astro.com.my" lang="en" xmltv_id="WarnerTVAsia.us" site_id="270" logo="https://divign0fdw3sv.cloudfront.net/Images/ChannelLogo/contenthub/270_144.png">Warner TV HD</channel>
  <channel site="content.astro.com.my" lang="en" xmltv_id="WWENetwork.us" site_id="194" logo="https://divign0fdw3sv.cloudfront.net/Images/ChannelLogo/contenthub/194_144.png">WWE Network</channel>
  <channel site="content.astro.com.my" lang="en" xmltv_id="ZeeTamil.in" site_id="297" logo="https://divign0fdw3sv.cloudfront.net/Images/ChannelLogo/contenthub/297_144.png">Zee Tamil HD</channel>
  <channel site="content.astro.com.my" lang="ms" xmltv_id="" site_id="14" logo="https://divign0fdw3sv.cloudfront.net/Images/ChannelLogo/contenthub/14_144.png">ERA FM</channel>
  <channel site="content.astro.com.my" lang="ms" xmltv_id="" site_id="15" logo="https://divign0fdw3sv.cloudfront.net/Images/ChannelLogo/contenthub/15_144.png">MY FM</channel>
  <channel site="content.astro.com.my" lang="ms" xmltv_id="" site_id="16" logo="https://divign0fdw3sv.cloudfront.net/Images/ChannelLogo/contenthub/16_144.png">OPUS</channel>
  <channel site="content.astro.com.my" lang="ms" xmltv_id="" site_id="17" logo="https://divign0fdw3sv.cloudfront.net/Images/ChannelLogo/contenthub/17_144.png">HITZ FM</channel>
  <channel site="content.astro.com.my" lang="ms" xmltv_id="" site_id="18" logo="https://divign0fdw3sv.cloudfront.net/Images/ChannelLogo/contenthub/18_144.png">MIX FM</channel>
  <channel site="content.astro.com.my" lang="ms" xmltv_id="" site_id="19" logo="https://divign0fdw3sv.cloudfront.net/Images/ChannelLogo/contenthub/19_144.png">LITE FM</channel>
  <channel site="content.astro.com.my" lang="ms" xmltv_id="" site_id="20" logo="https://divign0fdw3sv.cloudfront.net/Images/ChannelLogo/contenthub/20_144.png">CLASSIC ROCK</channel>
  <channel site="content.astro.com.my" lang="ms" xmltv_id="" site_id="21" logo="https://divign0fdw3sv.cloudfront.net/Images/ChannelLogo/contenthub/21_144.png">GOLD</channel>
  <channel site="content.astro.com.my" lang="ms" xmltv_id="" site_id="22" logo="https://divign0fdw3sv.cloudfront.net/Images/ChannelLogo/contenthub/22_144.png">THR GEGAR</channel>
  <channel site="content.astro.com.my" lang="ms" xmltv_id="" site_id="23" logo="https://divign0fdw3sv.cloudfront.net/Images/ChannelLogo/contenthub/23_144.png">INDIA BEAT</channel>
  <channel site="content.astro.com.my" lang="ms" xmltv_id="" site_id="24" logo="https://divign0fdw3sv.cloudfront.net/Images/ChannelLogo/contenthub/24_144.png">JAZZ</channel>
  <channel site="content.astro.com.my" lang="ms" xmltv_id="" site_id="25" logo="https://divign0fdw3sv.cloudfront.net/Images/ChannelLogo/contenthub/25_144.png">NAS FM</channel>
  <channel site="content.astro.com.my" lang="ms" xmltv_id="" site_id="26" logo="https://divign0fdw3sv.cloudfront.net/Images/ChannelLogo/contenthub/26_144.png">SINAR FM</channel>
  <channel site="content.astro.com.my" lang="ms" xmltv_id="" site_id="27" logo="https://divign0fdw3sv.cloudfront.net/Images/ChannelLogo/contenthub/27_144.png">OSAI</channel>
  <channel site="content.astro.com.my" lang="ms" xmltv_id="" site_id="28" logo="https://divign0fdw3sv.cloudfront.net/Images/ChannelLogo/contenthub/28_144.png">MELODY FM</channel>
  <channel site="content.astro.com.my" lang="ms" xmltv_id="" site_id="29" logo="https://divign0fdw3sv.cloudfront.net/Images/ChannelLogo/contenthub/29_144.png">V FM</channel>
  <channel site="content.astro.com.my" lang="ms" xmltv_id="" site_id="30" logo="https://divign0fdw3sv.cloudfront.net/Images/ChannelLogo/contenthub/30_144.png">THR RAAGA</channel>
  <channel site="content.astro.com.my" lang="ms" xmltv_id="" site_id="31" logo="https://divign0fdw3sv.cloudfront.net/Images/ChannelLogo/contenthub/31_144.png">BAYU</channel>
  <channel site="content.astro.com.my" lang="ms" xmltv_id="" site_id="32" logo="https://divign0fdw3sv.cloudfront.net/Images/ChannelLogo/contenthub/32_144.png">KENYALANG</channel>
  <channel site="content.astro.com.my" lang="ms" xmltv_id="" site_id="145" logo="https://divign0fdw3sv.cloudfront.net/Images/ChannelLogo/contenthub/145_144.png">WAI FM</channel>
  <channel site="content.astro.com.my" lang="ms" xmltv_id="" site_id="292" logo="https://divign0fdw3sv.cloudfront.net/Images/ChannelLogo/contenthub/292_144.png">ZAYAN</channel>
  <channel site="content.astro.com.my" lang="ms" xmltv_id="" site_id="293" logo="https://divign0fdw3sv.cloudfront.net/Images/ChannelLogo/contenthub/293_144.png">GOXUAN</channel>
  <channel site="content.astro.com.my" lang="ms" xmltv_id="" site_id="303" logo="https://divign0fdw3sv.cloudfront.net/Images/ChannelLogo/contenthub/303_144.png">AI FM</channel>
  <channel site="content.astro.com.my" lang="ms" xmltv_id="" site_id="310" logo="https://divign0fdw3sv.cloudfront.net/Images/ChannelLogo/contenthub/310_144.png">ASYIK FM</channel>
  <channel site="content.astro.com.my" lang="ms" xmltv_id="" site_id="311" logo="https://divign0fdw3sv.cloudfront.net/Images/ChannelLogo/contenthub/311_144.png">MINNAL FM</channel>
  <channel site="content.astro.com.my" lang="ms" xmltv_id="" site_id="312" logo="https://divign0fdw3sv.cloudfront.net/Images/ChannelLogo/contenthub/312_144.png">TRAXX FM</channel>
  <channel site="content.astro.com.my" lang="ms" xmltv_id="" site_id="394" logo="https://divign0fdw3sv.cloudfront.net/Images/ChannelLogo/contenthub/394_144.png">Smithsonian Channel</channel>
  <channel site="content.astro.com.my" lang="ms" xmltv_id="" site_id="459" logo="https://divign0fdw3sv.cloudfront.net/Images/ChannelLogo/contenthub/459_144.png">BBC Brit HD</channel>
  <channel site="content.astro.com.my" lang="ms" xmltv_id="" site_id="461" logo="https://divign0fdw3sv.cloudfront.net/Images/ChannelLogo/contenthub/461_144.png">ABC Australia HD</channel>
  <channel site="content.astro.com.my" lang="ms" xmltv_id="" site_id="467" logo="https://divign0fdw3sv.cloudfront.net/Images/ChannelLogo/contenthub/467_144.png">TV Okey HD</channel>
  <channel site="content.astro.com.my" lang="ms" xmltv_id="" site_id="472" logo="https://divign0fdw3sv.cloudfront.net/Images/ChannelLogo/contenthub/472_144.png">Love Nature 4K</channel>
  <channel site="content.astro.com.my" lang="ms" xmltv_id="" site_id="474" logo="https://divign0fdw3sv.cloudfront.net/Images/ChannelLogo/contenthub/474_144.png">SPOTV2</channel>
  <channel site="content.astro.com.my" lang="ms" xmltv_id="" site_id="476" logo="https://divign0fdw3sv.cloudfront.net/Images/ChannelLogo/contenthub/476_144.png">Sun Life</channel>
  <channel site="content.astro.com.my" lang="ms" xmltv_id="" site_id="477" logo="https://divign0fdw3sv.cloudfront.net/Images/ChannelLogo/contenthub/477_144.png">KTV</channel>
  <channel site="content.astro.com.my" lang="ms" xmltv_id="" site_id="478" logo="https://divign0fdw3sv.cloudfront.net/Images/ChannelLogo/contenthub/478_144.png">Sun News</channel>
  <channel site="content.astro.com.my" lang="ms" xmltv_id="" site_id="481" logo="https://divign0fdw3sv.cloudfront.net/Images/ChannelLogo/contenthub/481_144.png">CBeebies</channel>
  <channel site="content.astro.com.my" lang="ms" xmltv_id="" site_id="482" logo="https://divign0fdw3sv.cloudfront.net/Images/ChannelLogo/contenthub/482_144.png">Global Trekker</channel>
  <channel site="content.astro.com.my" lang="ms" xmltv_id="" site_id="483" logo="https://divign0fdw3sv.cloudfront.net/Images/ChannelLogo/contenthub/483_144.png">Love Nature</channel>
  <channel site="content.astro.com.my" lang="ms" xmltv_id="" site_id="485" logo="https://divign0fdw3sv.cloudfront.net/Images/ChannelLogo/contenthub/485_144.png">DreamWorks</channel>
  <channel site="content.astro.com.my" lang="ms" xmltv_id="" site_id="486" logo="https://divign0fdw3sv.cloudfront.net/Images/ChannelLogo/contenthub/486_144.png">Arena Bola</channel>
  <channel site="content.astro.com.my" lang="ms" xmltv_id="" site_id="487" logo="https://divign0fdw3sv.cloudfront.net/Images/ChannelLogo/contenthub/487_144.png">Arena Bola 2</channel>
  <channel site="content.astro.com.my" lang="ms" xmltv_id="" site_id="490" logo="https://divign0fdw3sv.cloudfront.net/Images/ChannelLogo/contenthub/490_144.png">Zee Cinema</channel>
  <channel site="content.astro.com.my" lang="ms" xmltv_id="" site_id="503" logo="https://divign0fdw3sv.cloudfront.net/Images/ChannelLogo/contenthub/503_144.png">W-Sport</channel>
  <channel site="content.astro.com.my" lang="ms" xmltv_id="" site_id="508" logo="https://divign0fdw3sv.cloudfront.net/Images/ChannelLogo/contenthub/508_144.png">Astro Premier</channel>
  <channel site="content.astro.com.my" lang="ms" xmltv_id="" site_id="524" logo="https://divign0fdw3sv.cloudfront.net/Images/ChannelLogo/contenthub/524_144.png">HITS NOW</channel>
  <channel site="content.astro.com.my" lang="ms" xmltv_id="" site_id="534" logo="https://divign0fdw3sv.cloudfront.net/Images/ChannelLogo/contenthub/534_144.png">Arena Bola 3</channel>
  <channel site="content.astro.com.my" lang="ms" xmltv_id="" site_id="535" logo="https://divign0fdw3sv.cloudfront.net/Images/ChannelLogo/contenthub/535_144.png">Arena Bola 4</channel>
  <channel site="content.astro.com.my" lang="ms" xmltv_id="" site_id="536" logo="https://divign0fdw3sv.cloudfront.net/Images/ChannelLogo/contenthub/536_144.png">Astro Premier League</channel>
  <channel site="content.astro.com.my" lang="ms" xmltv_id="" site_id="537" logo="https://divign0fdw3sv.cloudfront.net/Images/ChannelLogo/contenthub/537_144.png">Astro Premier League 2</channel>
  <channel site="content.astro.com.my" lang="ms" xmltv_id="" site_id="538" logo="https://divign0fdw3sv.cloudfront.net/Images/ChannelLogo/contenthub/538_144.png">Astro Premier League 3</channel>
  <channel site="content.astro.com.my" lang="ms" xmltv_id="" site_id="539" logo="https://divign0fdw3sv.cloudfront.net/Images/ChannelLogo/contenthub/539_144.png">Astro Football</channel>
  <channel site="content.astro.com.my" lang="ms" xmltv_id="" site_id="540" logo="https://divign0fdw3sv.cloudfront.net/Images/ChannelLogo/contenthub/540_144.png">Astro Badminton</channel>
  <channel site="content.astro.com.my" lang="ms" xmltv_id="" site_id="542" logo="https://divign0fdw3sv.cloudfront.net/Images/ChannelLogo/contenthub/542_144.png">Astro Sports Plus</channel>
  <channel site="content.astro.com.my" lang="ms" xmltv_id="" site_id="543" logo="https://divign0fdw3sv.cloudfront.net/Images/ChannelLogo/contenthub/543_144.png">Astro Grandstand</channel>
  <channel site="content.astro.com.my" lang="ms" xmltv_id="" site_id="564" logo="https://divign0fdw3sv.cloudfront.net/Images/ChannelLogo/contenthub/564_144.png">LOL</channel>
  <channel site="content.astro.com.my" lang="ms" xmltv_id="" site_id="568" logo="https://divign0fdw3sv.cloudfront.net/Images/ChannelLogo/contenthub/568_144.png">Astro Premier League 4</channel>
  <channel site="content.astro.com.my" lang="ms" xmltv_id="" site_id="570" logo="https://divign0fdw3sv.cloudfront.net/Images/ChannelLogo/contenthub/570_144.png">Astro Premier League 5</channel>
  <channel site="content.astro.com.my" lang="ms" xmltv_id="" site_id="571" logo="https://divign0fdw3sv.cloudfront.net/Images/ChannelLogo/contenthub/571_144.png">RUSI</channel>
  <channel site="content.astro.com.my" lang="ms" xmltv_id="" site_id="572" logo="https://divign0fdw3sv.cloudfront.net/Images/ChannelLogo/contenthub/572_144.png">Astro Shaw</channel>
  <channel site="content.astro.com.my" lang="ms" xmltv_id="8TV.my" site_id="115" logo="https://divign0fdw3sv.cloudfront.net/Images/ChannelLogo/contenthub/115_144.png">8TV</channel>
  <channel site="content.astro.com.my" lang="ms" xmltv_id="AstroArena2.my" site_id="457" logo="https://divign0fdw3sv.cloudfront.net/Images/ChannelLogo/contenthub/457_144.png">Astro Arena 2</channel>
  <channel site="content.astro.com.my" lang="ms" xmltv_id="AstroArena.my" site_id="235" logo="https://divign0fdw3sv.cloudfront.net/Images/ChannelLogo/contenthub/235_144.png">Astro Arena</channel>
  <channel site="content.astro.com.my" lang="ms" xmltv_id="AstroAura.my" site_id="400" logo="https://divign0fdw3sv.cloudfront.net/Images/ChannelLogo/contenthub/400_144.png">Astro Aura HD</channel>
  <channel site="content.astro.com.my" lang="ms" xmltv_id="AstroAwani.my" site_id="436" logo="https://divign0fdw3sv.cloudfront.net/Images/ChannelLogo/contenthub/436_144.png">Astro Awani HD</channel>
  <channel site="content.astro.com.my" lang="ms" xmltv_id="AstroCeria.my" site_id="386" logo="https://divign0fdw3sv.cloudfront.net/Images/ChannelLogo/contenthub/386_144.png">Astro Ceria HD</channel>
  <channel site="content.astro.com.my" lang="ms" xmltv_id="AstroCitra.my" site_id="301" logo="https://divign0fdw3sv.cloudfront.net/Images/ChannelLogo/contenthub/301_144.png">Astro Citra HD</channel>
  <channel site="content.astro.com.my" lang="ms" xmltv_id="AstroCricket.my" site_id="197" logo="https://divign0fdw3sv.cloudfront.net/Images/ChannelLogo/contenthub/197_144.png">Astro Cricket</channel>
  <channel site="content.astro.com.my" lang="ms" xmltv_id="AstroOasis.my" site_id="315" logo="https://divign0fdw3sv.cloudfront.net/Images/ChannelLogo/contenthub/315_144.png">Astro Oasis HD</channel>
  <channel site="content.astro.com.my" lang="ms" xmltv_id="AstroPrima.my" site_id="316" logo="https://divign0fdw3sv.cloudfront.net/Images/ChannelLogo/contenthub/316_144.png">Astro Prima HD</channel>
  <channel site="content.astro.com.my" lang="ms" xmltv_id="AstroRia.my" site_id="193" logo="https://divign0fdw3sv.cloudfront.net/Images/ChannelLogo/contenthub/193_144.png">Astro Ria HD</channel>
  <channel site="content.astro.com.my" lang="ms" xmltv_id="AstroTutorTVSPM.my" site_id="411" logo="https://divign0fdw3sv.cloudfront.net/Images/ChannelLogo/contenthub/411_144.png">Astro Tutor TV</channel>
  <channel site="content.astro.com.my" lang="ms" xmltv_id="AstroWahLaiToi.my" site_id="129" logo="https://divign0fdw3sv.cloudfront.net/Images/ChannelLogo/contenthub/129_144.png">Astro Wah Lai Toi HD</channel>
  <channel site="content.astro.com.my" lang="ms" xmltv_id="AstroWarna.my" site_id="272" logo="https://divign0fdw3sv.cloudfront.net/Images/ChannelLogo/contenthub/272_144.png">Astro Warna HD</channel>
  <channel site="content.astro.com.my" lang="ms" xmltv_id="BBCFirstAsia.uk" site_id="458" logo="https://divign0fdw3sv.cloudfront.net/Images/ChannelLogo/contenthub/458_144.png">BBC First HD</channel>
  <channel site="content.astro.com.my" lang="ms" xmltv_id="BernamaTV.my" site_id="160" logo="https://divign0fdw3sv.cloudfront.net/Images/ChannelLogo/contenthub/160_144.png">BERNAMA</channel>
  <channel site="content.astro.com.my" lang="ms" xmltv_id="NTV7.my" site_id="93" logo="https://divign0fdw3sv.cloudfront.net/Images/ChannelLogo/contenthub/93_144.png">NTV7</channel>
  <channel site="content.astro.com.my" lang="ms" xmltv_id="TV1.my" site_id="395" logo="https://divign0fdw3sv.cloudfront.net/Images/ChannelLogo/contenthub/395_144.png">TV1 HD</channel>
  <channel site="content.astro.com.my" lang="ms" xmltv_id="TV2.my" site_id="396" logo="https://divign0fdw3sv.cloudfront.net/Images/ChannelLogo/contenthub/396_144.png">TV2 HD</channel>
  <channel site="content.astro.com.my" lang="ms" xmltv_id="TV3.my" site_id="106" logo="https://divign0fdw3sv.cloudfront.net/Images/ChannelLogo/contenthub/106_144.png">TV3</channel>
  <channel site="content.astro.com.my" lang="ms" xmltv_id="TV9.my" site_id="48" logo="https://divign0fdw3sv.cloudfront.net/Images/ChannelLogo/contenthub/48_144.png">TV9</channel>
  <channel site="content.astro.com.my" lang="ms" xmltv_id="TVAlhijrah.my" site_id="149" logo="https://divign0fdw3sv.cloudfront.net/Images/ChannelLogo/contenthub/149_144.png">Al-Hijrah</channel>
  <channel site="content.astro.com.my" lang="ms" xmltv_id="TVS.my" site_id="429" logo="https://divign0fdw3sv.cloudfront.net/Images/ChannelLogo/contenthub/429_144.png">TV Sarawak</channel>
</channels>
